livescore_api/__init__.py
livescore_api/__main__.py
livescore_api/console.py
livescore_api/main.py
livescore_api-0.0.1.dist-info/METADATA
livescore_api-0.0.1.dist-info/WHEEL
livescore_api-0.0.1.dist-info/entry_points.txt
livescore_api-0.0.1.dist-info/top_level.txt
livescore_api-0.0.1.dist-info/RECORD
