Metadata-Version: 2.1
Name: livescore-api
Version: 0.0.1
Summary: Access and manipulate matches from Livescore.com
Home-page: https://github.com/Simatwa/livescore-api
Author: Smartwa
Author-email: smartwacaleb@gmail.com
Maintainer: Smartwa
License: MIT
Project-URL: Bug Report, https://github.com/Simatwa/livescore-api/issues/new
Keywords: livescore,football,livescore-api,api
Classifier: License :: OSI Approved :: MIT License
Classifier: Development Status :: 4 - Beta
Classifier: Intended Audience :: Developers
Classifier: Natural Language :: English
Classifier: License :: Free For Home Use
Classifier: Intended Audience :: Customer Service
Classifier: Programming Language :: Python
Classifier: Topic :: Software Development :: Libraries :: Python Modules
Classifier: Programming Language :: Python :: 3 :: Only
Classifier: Programming Language :: Python :: 3.8
Classifier: Programming Language :: Python :: 3.9
Classifier: Programming Language :: Python :: 3.10
Classifier: Programming Language :: Python :: 3.11
Requires-Dist: argparse
Requires-Dist: pandas
Requires-Dist: requests (>=2.28.2)
Requires-Dist: tabulate
